<?xml version="1.0" ?>
<Gesture Subject="1" InputType="Touch" Speed="Medium" Name="two06" NumPts="105">
	<Stroke index="1">
		<Point X="287" Y="207" T="1" Pressure="128"/>
		<Point X="287" Y="206" T="2" Pressure="128"/>
		<Point X="287" Y="205" T="3" Pressure="128"/>
		<Point X="287" Y="204" T="4" Pressure="128"/>
		<Point X="287" Y="203" T="5" Pressure="128"/>
		<Point X="287" Y="202" T="6" Pressure="128"/>
		<Point X="287" Y="201" T="7" Pressure="128"/>
		<Point X="287" Y="199" T="8" Pressure="128"/>
		<Point X="287" Y="197" T="9" Pressure="128"/>
		<Point X="287" Y="196" T="10" Pressure="128"/>
		<Point X="288" Y="194" T="11" Pressure="128"/>
		<Point X="289" Y="192" T="12" Pressure="128"/>
		<Point X="290" Y="190" T="13" Pressure="128"/>
		<Point X="292" Y="188" T="14" Pressure="128"/>
		<Point X="293" Y="187" T="15" Pressure="128"/>
		<Point X="295" Y="185" T="16" Pressure="128"/>
		<Point X="299" Y="182" T="17" Pressure="128"/>
		<Point X="301" Y="181" T="18" Pressure="128"/>
		<Point X="303" Y="180" T="19" Pressure="128"/>
		<Point X="307" Y="179" T="20" Pressure="128"/>
		<Point X="309" Y="178" T="21" Pressure="128"/>
		<Point X="312" Y="178" T="22" Pressure="128"/>
		<Point X="314" Y="178" T="23" Pressure="128"/>
		<Point X="316" Y="178" T="24" Pressure="128"/>
		<Point X="319" Y="178" T="25" Pressure="128"/>
		<Point X="320" Y="178" T="26" Pressure="128"/>
		<Point X="323" Y="178" T="27" Pressure="128"/>
		<Point X="325" Y="178" T="28" Pressure="128"/>
		<Point X="327" Y="179" T="29" Pressure="128"/>
		<Point X="328" Y="180" T="30" Pressure="128"/>
		<Point X="330" Y="181" T="31" Pressure="128"/>
		<Point X="331" Y="183" T="32" Pressure="128"/>
		<Point X="333" Y="184" T="33" Pressure="128"/>
		<Point X="334" Y="185" T="34" Pressure="128"/>
		<Point X="335" Y="187" T="35" Pressure="128"/>
		<Point X="336" Y="188" T="36" Pressure="128"/>
		<Point X="336" Y="190" T="37" Pressure="128"/>
		<Point X="338" Y="192" T="38" Pressure="128"/>
		<Point X="338" Y="197" T="39" Pressure="128"/>
		<Point X="338" Y="199" T="40" Pressure="128"/>
		<Point X="338" Y="202" T="41" Pressure="128"/>
		<Point X="338" Y="204" T="42" Pressure="128"/>
		<Point X="338" Y="207" T="43" Pressure="128"/>
		<Point X="338" Y="210" T="44" Pressure="128"/>
		<Point X="337" Y="213" T="45" Pressure="128"/>
		<Point X="335" Y="219" T="46" Pressure="128"/>
		<Point X="335" Y="222" T="47" Pressure="128"/>
		<Point X="333" Y="226" T="48" Pressure="128"/>
		<Point X="332" Y="229" T="49" Pressure="128"/>
		<Point X="331" Y="233" T="50" Pressure="128"/>
		<Point X="329" Y="236" T="51" Pressure="128"/>
		<Point X="327" Y="239" T="52" Pressure="128"/>
		<Point X="326" Y="241" T="53" Pressure="128"/>
		<Point X="324" Y="244" T="54" Pressure="128"/>
		<Point X="323" Y="247" T="55" Pressure="128"/>
		<Point X="321" Y="251" T="56" Pressure="128"/>
		<Point X="320" Y="253" T="57" Pressure="128"/>
		<Point X="317" Y="256" T="58" Pressure="128"/>
		<Point X="314" Y="261" T="59" Pressure="128"/>
		<Point X="312" Y="264" T="60" Pressure="128"/>
		<Point X="311" Y="266" T="61" Pressure="128"/>
		<Point X="308" Y="268" T="62" Pressure="128"/>
		<Point X="307" Y="271" T="63" Pressure="128"/>
		<Point X="304" Y="275" T="64" Pressure="128"/>
		<Point X="302" Y="277" T="65" Pressure="128"/>
		<Point X="301" Y="278" T="66" Pressure="128"/>
		<Point X="299" Y="280" T="67" Pressure="128"/>
		<Point X="298" Y="282" T="68" Pressure="128"/>
		<Point X="297" Y="283" T="69" Pressure="128"/>
		<Point X="296" Y="284" T="70" Pressure="128"/>
		<Point X="294" Y="286" T="71" Pressure="128"/>
		<Point X="293" Y="287" T="72" Pressure="128"/>
		<Point X="293" Y="288" T="73" Pressure="128"/>
		<Point X="292" Y="289" T="74" Pressure="128"/>
		<Point X="291" Y="290" T="75" Pressure="128"/>
		<Point X="291" Y="291" T="76" Pressure="128"/>
		<Point X="291" Y="292" T="77" Pressure="128"/>
		<Point X="292" Y="292" T="78" Pressure="128"/>
		<Point X="293" Y="292" T="79" Pressure="128"/>
		<Point X="297" Y="292" T="80" Pressure="128"/>
		<Point X="299" Y="291" T="81" Pressure="128"/>
		<Point X="303" Y="290" T="82" Pressure="128"/>
		<Point X="305" Y="290" T="83" Pressure="128"/>
		<Point X="308" Y="289" T="84" Pressure="128"/>
		<Point X="315" Y="288" T="85" Pressure="128"/>
		<Point X="321" Y="286" T="86" Pressure="128"/>
		<Point X="325" Y="285" T="87" Pressure="128"/>
		<Point X="329" Y="284" T="88" Pressure="128"/>
		<Point X="338" Y="283" T="89" Pressure="128"/>
		<Point X="341" Y="282" T="90" Pressure="128"/>
		<Point X="345" Y="281" T="91" Pressure="128"/>
		<Point X="348" Y="281" T="92" Pressure="128"/>
		<Point X="351" Y="280" T="93" Pressure="128"/>
		<Point X="361" Y="279" T="94" Pressure="128"/>
		<Point X="364" Y="279" T="95" Pressure="128"/>
		<Point X="366" Y="279" T="96" Pressure="128"/>
		<Point X="369" Y="279" T="97" Pressure="128"/>
		<Point X="371" Y="279" T="98" Pressure="128"/>
		<Point X="372" Y="279" T="99" Pressure="128"/>
		<Point X="375" Y="279" T="100" Pressure="128"/>
		<Point X="376" Y="279" T="101" Pressure="128"/>
		<Point X="377" Y="279" T="102" Pressure="128"/>
		<Point X="378" Y="280" T="103" Pressure="128"/>
		<Point X="378" Y="281" T="104" Pressure="128"/>
		<Point X="378" Y="282" T="105" Pressure="128"/>
	</Stroke>
</Gesture>
