<?xml version="1.0" ?>
<Gesture Subject="1" InputType="Touch" Speed="Medium" Name="four09" NumPts="170">
	<Stroke index="1">
		<Point X="330" Y="104" T="1" Pressure="128"/>
		<Point X="331" Y="103" T="2" Pressure="128"/>
		<Point X="331" Y="102" T="3" Pressure="128"/>
		<Point X="331" Y="103" T="4" Pressure="128"/>
		<Point X="331" Y="104" T="5" Pressure="128"/>
		<Point X="331" Y="106" T="6" Pressure="128"/>
		<Point X="331" Y="107" T="7" Pressure="128"/>
		<Point X="331" Y="108" T="8" Pressure="128"/>
		<Point X="331" Y="112" T="9" Pressure="128"/>
		<Point X="330" Y="114" T="10" Pressure="128"/>
		<Point X="330" Y="115" T="11" Pressure="128"/>
		<Point X="328" Y="120" T="12" Pressure="128"/>
		<Point X="327" Y="123" T="13" Pressure="128"/>
		<Point X="326" Y="127" T="14" Pressure="128"/>
		<Point X="324" Y="131" T="15" Pressure="128"/>
		<Point X="323" Y="134" T="16" Pressure="128"/>
		<Point X="321" Y="139" T="17" Pressure="128"/>
		<Point X="320" Y="142" T="18" Pressure="128"/>
		<Point X="316" Y="152" T="19" Pressure="128"/>
		<Point X="315" Y="156" T="20" Pressure="128"/>
		<Point X="313" Y="160" T="21" Pressure="128"/>
		<Point X="312" Y="164" T="22" Pressure="128"/>
		<Point X="311" Y="168" T="23" Pressure="128"/>
		<Point X="309" Y="172" T="24" Pressure="128"/>
		<Point X="308" Y="177" T="25" Pressure="128"/>
		<Point X="305" Y="185" T="26" Pressure="128"/>
		<Point X="303" Y="189" T="27" Pressure="128"/>
		<Point X="301" Y="193" T="28" Pressure="128"/>
		<Point X="297" Y="202" T="29" Pressure="128"/>
		<Point X="296" Y="206" T="30" Pressure="128"/>
		<Point X="294" Y="210" T="31" Pressure="128"/>
		<Point X="290" Y="219" T="32" Pressure="128"/>
		<Point X="287" Y="223" T="33" Pressure="128"/>
		<Point X="285" Y="228" T="34" Pressure="128"/>
		<Point X="281" Y="236" T="35" Pressure="128"/>
		<Point X="278" Y="239" T="36" Pressure="128"/>
		<Point X="277" Y="243" T="37" Pressure="128"/>
		<Point X="272" Y="252" T="38" Pressure="128"/>
		<Point X="271" Y="256" T="39" Pressure="128"/>
		<Point X="268" Y="259" T="40" Pressure="128"/>
		<Point X="266" Y="266" T="41" Pressure="128"/>
		<Point X="264" Y="271" T="42" Pressure="128"/>
		<Point X="262" Y="274" T="43" Pressure="128"/>
		<Point X="260" Y="281" T="44" Pressure="128"/>
		<Point X="259" Y="284" T="45" Pressure="128"/>
		<Point X="257" Y="287" T="46" Pressure="128"/>
		<Point X="255" Y="293" T="47" Pressure="128"/>
		<Point X="254" Y="296" T="48" Pressure="128"/>
		<Point X="252" Y="299" T="49" Pressure="128"/>
		<Point X="251" Y="304" T="50" Pressure="128"/>
		<Point X="249" Y="307" T="51" Pressure="128"/>
		<Point X="248" Y="310" T="52" Pressure="128"/>
		<Point X="247" Y="315" T="53" Pressure="128"/>
		<Point X="246" Y="317" T="54" Pressure="128"/>
		<Point X="245" Y="319" T="55" Pressure="128"/>
		<Point X="244" Y="323" T="56" Pressure="128"/>
		<Point X="244" Y="325" T="57" Pressure="128"/>
		<Point X="243" Y="327" T="58" Pressure="128"/>
		<Point X="242" Y="329" T="59" Pressure="128"/>
		<Point X="242" Y="331" T="60" Pressure="128"/>
		<Point X="242" Y="332" T="61" Pressure="128"/>
		<Point X="242" Y="334" T="62" Pressure="128"/>
		<Point X="242" Y="335" T="63" Pressure="128"/>
		<Point X="242" Y="337" T="64" Pressure="128"/>
		<Point X="242" Y="338" T="65" Pressure="128"/>
		<Point X="243" Y="338" T="66" Pressure="128"/>
		<Point X="244" Y="339" T="67" Pressure="128"/>
		<Point X="246" Y="339" T="68" Pressure="128"/>
		<Point X="248" Y="339" T="69" Pressure="128"/>
		<Point X="249" Y="339" T="70" Pressure="128"/>
		<Point X="253" Y="339" T="71" Pressure="128"/>
		<Point X="256" Y="339" T="72" Pressure="128"/>
		<Point X="259" Y="339" T="73" Pressure="128"/>
		<Point X="267" Y="337" T="74" Pressure="128"/>
		<Point X="271" Y="337" T="75" Pressure="128"/>
		<Point X="275" Y="336" T="76" Pressure="128"/>
		<Point X="286" Y="334" T="77" Pressure="128"/>
		<Point X="292" Y="334" T="78" Pressure="128"/>
		<Point X="297" Y="333" T="79" Pressure="128"/>
		<Point X="303" Y="332" T="80" Pressure="128"/>
		<Point X="308" Y="332" T="81" Pressure="128"/>
		<Point X="316" Y="331" T="82" Pressure="128"/>
		<Point X="321" Y="330" T="83" Pressure="128"/>
		<Point X="333" Y="329" T="84" Pressure="128"/>
		<Point X="339" Y="328" T="85" Pressure="128"/>
		<Point X="346" Y="328" T="86" Pressure="128"/>
		<Point X="359" Y="327" T="87" Pressure="128"/>
		<Point X="365" Y="327" T="88" Pressure="128"/>
		<Point X="372" Y="326" T="89" Pressure="128"/>
		<Point X="387" Y="324" T="90" Pressure="128"/>
		<Point X="395" Y="324" T="91" Pressure="128"/>
		<Point X="402" Y="323" T="92" Pressure="128"/>
		<Point X="417" Y="322" T="93" Pressure="128"/>
		<Point X="424" Y="322" T="94" Pressure="128"/>
		<Point X="431" Y="322" T="95" Pressure="128"/>
		<Point X="445" Y="321" T="96" Pressure="128"/>
		<Point X="452" Y="321" T="97" Pressure="128"/>
		<Point X="459" Y="320" T="98" Pressure="128"/>
		<Point X="470" Y="319" T="99" Pressure="128"/>
		<Point X="477" Y="319" T="100" Pressure="128"/>
		<Point X="481" Y="319" T="101" Pressure="128"/>
		<Point X="492" Y="319" T="102" Pressure="128"/>
		<Point X="496" Y="319" T="103" Pressure="128"/>
		<Point X="500" Y="319" T="104" Pressure="128"/>
		<Point X="508" Y="319" T="105" Pressure="128"/>
		<Point X="511" Y="319" T="106" Pressure="128"/>
		<Point X="514" Y="319" T="107" Pressure="128"/>
		<Point X="519" Y="319" T="108" Pressure="128"/>
		<Point X="524" Y="318" T="109" Pressure="128"/>
		<Point X="527" Y="318" T="110" Pressure="128"/>
		<Point X="529" Y="318" T="111" Pressure="128"/>
		<Point X="530" Y="318" T="112" Pressure="128"/>
		<Point X="532" Y="318" T="113" Pressure="128"/>
		<Point X="533" Y="318" T="114" Pressure="128"/>
		<Point X="532" Y="317" T="115" Pressure="128"/>
		<Point X="530" Y="317" T="116" Pressure="128"/>
	</Stroke>
	<Stroke index="2">
		<Point X="411" Y="216" T="117" Pressure="128"/>
		<Point X="410" Y="216" T="118" Pressure="128"/>
		<Point X="410" Y="217" T="119" Pressure="128"/>
		<Point X="408" Y="218" T="120" Pressure="128"/>
		<Point X="407" Y="221" T="121" Pressure="128"/>
		<Point X="406" Y="225" T="122" Pressure="128"/>
		<Point X="406" Y="230" T="123" Pressure="128"/>
		<Point X="406" Y="234" T="124" Pressure="128"/>
		<Point X="406" Y="237" T="125" Pressure="128"/>
		<Point X="406" Y="240" T="126" Pressure="128"/>
		<Point X="406" Y="244" T="127" Pressure="128"/>
		<Point X="406" Y="256" T="128" Pressure="128"/>
		<Point X="406" Y="260" T="129" Pressure="128"/>
		<Point X="406" Y="264" T="130" Pressure="128"/>
		<Point X="406" Y="268" T="131" Pressure="128"/>
		<Point X="406" Y="277" T="132" Pressure="128"/>
		<Point X="406" Y="282" T="133" Pressure="128"/>
		<Point X="406" Y="287" T="134" Pressure="128"/>
		<Point X="407" Y="296" T="135" Pressure="128"/>
		<Point X="407" Y="301" T="136" Pressure="128"/>
		<Point X="407" Y="306" T="137" Pressure="128"/>
		<Point X="407" Y="317" T="138" Pressure="128"/>
		<Point X="408" Y="322" T="139" Pressure="128"/>
		<Point X="409" Y="327" T="140" Pressure="128"/>
		<Point X="409" Y="338" T="141" Pressure="128"/>
		<Point X="409" Y="343" T="142" Pressure="128"/>
		<Point X="409" Y="348" T="143" Pressure="128"/>
		<Point X="409" Y="353" T="144" Pressure="128"/>
		<Point X="409" Y="359" T="145" Pressure="128"/>
		<Point X="409" Y="363" T="146" Pressure="128"/>
		<Point X="409" Y="368" T="147" Pressure="128"/>
		<Point X="408" Y="378" T="148" Pressure="128"/>
		<Point X="408" Y="384" T="149" Pressure="128"/>
		<Point X="407" Y="388" T="150" Pressure="128"/>
		<Point X="406" Y="398" T="151" Pressure="128"/>
		<Point X="406" Y="403" T="152" Pressure="128"/>
		<Point X="405" Y="408" T="153" Pressure="128"/>
		<Point X="404" Y="416" T="154" Pressure="128"/>
		<Point X="403" Y="420" T="155" Pressure="128"/>
		<Point X="403" Y="424" T="156" Pressure="128"/>
		<Point X="402" Y="432" T="157" Pressure="128"/>
		<Point X="402" Y="435" T="158" Pressure="128"/>
		<Point X="401" Y="438" T="159" Pressure="128"/>
		<Point X="399" Y="444" T="160" Pressure="128"/>
		<Point X="399" Y="447" T="161" Pressure="128"/>
		<Point X="398" Y="450" T="162" Pressure="128"/>
		<Point X="395" Y="455" T="163" Pressure="128"/>
		<Point X="395" Y="457" T="164" Pressure="128"/>
		<Point X="394" Y="459" T="165" Pressure="128"/>
		<Point X="392" Y="462" T="166" Pressure="128"/>
		<Point X="391" Y="463" T="167" Pressure="128"/>
		<Point X="390" Y="465" T="168" Pressure="128"/>
		<Point X="389" Y="465" T="169" Pressure="128"/>
		<Point X="388" Y="466" T="170" Pressure="128"/>
	</Stroke>
</Gesture>
