<?xml version="1.0" ?>
<Gesture Subject="6" InputType="Touch" Speed="Medium" Name=")10" NumPts="56">
	<Stroke index="1">
		<Point X="448" Y="278" T="1" Pressure="128"/>
		<Point X="451" Y="281" T="2" Pressure="128"/>
		<Point X="454" Y="286" T="3" Pressure="128"/>
		<Point X="457" Y="291" T="4" Pressure="128"/>
		<Point X="460" Y="295" T="5" Pressure="128"/>
		<Point X="462" Y="298" T="6" Pressure="128"/>
		<Point X="463" Y="302" T="7" Pressure="128"/>
		<Point X="465" Y="307" T="8" Pressure="128"/>
		<Point X="466" Y="312" T="9" Pressure="128"/>
		<Point X="468" Y="318" T="10" Pressure="128"/>
		<Point X="469" Y="322" T="11" Pressure="128"/>
		<Point X="471" Y="325" T="12" Pressure="128"/>
		<Point X="472" Y="331" T="13" Pressure="128"/>
		<Point X="474" Y="337" T="14" Pressure="128"/>
		<Point X="476" Y="342" T="15" Pressure="128"/>
		<Point X="477" Y="346" T="16" Pressure="128"/>
		<Point X="478" Y="351" T="17" Pressure="128"/>
		<Point X="479" Y="356" T="18" Pressure="128"/>
		<Point X="479" Y="363" T="19" Pressure="128"/>
		<Point X="480" Y="368" T="20" Pressure="128"/>
		<Point X="480" Y="372" T="21" Pressure="128"/>
		<Point X="480" Y="376" T="22" Pressure="128"/>
		<Point X="480" Y="381" T="23" Pressure="128"/>
		<Point X="479" Y="387" T="24" Pressure="128"/>
		<Point X="479" Y="391" T="25" Pressure="128"/>
		<Point X="478" Y="395" T="26" Pressure="128"/>
		<Point X="477" Y="398" T="27" Pressure="128"/>
		<Point X="476" Y="401" T="28" Pressure="128"/>
		<Point X="475" Y="405" T="29" Pressure="128"/>
		<Point X="473" Y="410" T="30" Pressure="128"/>
		<Point X="472" Y="415" T="31" Pressure="128"/>
		<Point X="470" Y="420" T="32" Pressure="128"/>
		<Point X="470" Y="422" T="33" Pressure="128"/>
		<Point X="469" Y="424" T="34" Pressure="128"/>
		<Point X="468" Y="427" T="35" Pressure="128"/>
		<Point X="467" Y="431" T="36" Pressure="128"/>
		<Point X="465" Y="435" T="37" Pressure="128"/>
		<Point X="462" Y="440" T="38" Pressure="128"/>
		<Point X="457" Y="445" T="39" Pressure="128"/>
		<Point X="454" Y="448" T="40" Pressure="128"/>
		<Point X="450" Y="450" T="41" Pressure="128"/>
		<Point X="448" Y="453" T="42" Pressure="128"/>
		<Point X="446" Y="456" T="43" Pressure="128"/>
		<Point X="442" Y="459" T="44" Pressure="128"/>
		<Point X="438" Y="464" T="45" Pressure="128"/>
		<Point X="433" Y="469" T="46" Pressure="128"/>
		<Point X="428" Y="472" T="47" Pressure="128"/>
		<Point X="425" Y="475" T="48" Pressure="128"/>
		<Point X="422" Y="477" T="49" Pressure="128"/>
		<Point X="421" Y="479" T="50" Pressure="128"/>
		<Point X="419" Y="482" T="51" Pressure="128"/>
		<Point X="417" Y="484" T="52" Pressure="128"/>
		<Point X="416" Y="486" T="53" Pressure="128"/>
		<Point X="414" Y="488" T="54" Pressure="128"/>
		<Point X="413" Y="488" T="55" Pressure="128"/>
		<Point X="413" Y="488" T="56" Pressure="128"/>
	</Stroke>
</Gesture>
