<?xml version="1.0" ?>
<Gesture Subject="4" InputType="Touch" Speed="Medium" Name="five08" NumPts="129">
	<Stroke index="1">
		<Point X="307" Y="448" T="1" Pressure="128"/>
		<Point X="306" Y="447" T="2" Pressure="128"/>
		<Point X="306" Y="446" T="3" Pressure="128"/>
		<Point X="305" Y="446" T="4" Pressure="128"/>
		<Point X="303" Y="445" T="5" Pressure="128"/>
		<Point X="302" Y="445" T="6" Pressure="128"/>
		<Point X="301" Y="445" T="7" Pressure="128"/>
		<Point X="298" Y="446" T="8" Pressure="128"/>
		<Point X="296" Y="446" T="9" Pressure="128"/>
		<Point X="294" Y="447" T="10" Pressure="128"/>
		<Point X="293" Y="447" T="11" Pressure="128"/>
		<Point X="290" Y="448" T="12" Pressure="128"/>
		<Point X="288" Y="448" T="13" Pressure="128"/>
		<Point X="286" Y="449" T="14" Pressure="128"/>
		<Point X="281" Y="450" T="15" Pressure="128"/>
		<Point X="276" Y="451" T="16" Pressure="128"/>
		<Point X="274" Y="451" T="17" Pressure="128"/>
		<Point X="271" Y="451" T="18" Pressure="128"/>
		<Point X="270" Y="451" T="19" Pressure="128"/>
		<Point X="268" Y="451" T="20" Pressure="128"/>
		<Point X="265" Y="452" T="21" Pressure="128"/>
		<Point X="263" Y="452" T="22" Pressure="128"/>
		<Point X="262" Y="452" T="23" Pressure="128"/>
		<Point X="261" Y="452" T="24" Pressure="128"/>
		<Point X="260" Y="452" T="25" Pressure="128"/>
		<Point X="260" Y="453" T="26" Pressure="128"/>
		<Point X="261" Y="455" T="27" Pressure="128"/>
		<Point X="262" Y="456" T="28" Pressure="128"/>
		<Point X="262" Y="457" T="29" Pressure="128"/>
		<Point X="262" Y="458" T="30" Pressure="128"/>
		<Point X="263" Y="459" T="31" Pressure="128"/>
		<Point X="263" Y="461" T="32" Pressure="128"/>
		<Point X="263" Y="463" T="33" Pressure="128"/>
		<Point X="264" Y="464" T="34" Pressure="128"/>
		<Point X="264" Y="466" T="35" Pressure="128"/>
		<Point X="265" Y="471" T="36" Pressure="128"/>
		<Point X="266" Y="475" T="37" Pressure="128"/>
		<Point X="266" Y="478" T="38" Pressure="128"/>
		<Point X="266" Y="482" T="39" Pressure="128"/>
		<Point X="266" Y="486" T="40" Pressure="128"/>
		<Point X="267" Y="493" T="41" Pressure="128"/>
		<Point X="267" Y="497" T="42" Pressure="128"/>
		<Point X="267" Y="502" T="43" Pressure="128"/>
		<Point X="267" Y="505" T="44" Pressure="128"/>
		<Point X="267" Y="508" T="45" Pressure="128"/>
		<Point X="266" Y="513" T="46" Pressure="128"/>
		<Point X="265" Y="515" T="47" Pressure="128"/>
		<Point X="264" Y="517" T="48" Pressure="128"/>
		<Point X="263" Y="519" T="49" Pressure="128"/>
		<Point X="263" Y="520" T="50" Pressure="128"/>
		<Point X="262" Y="521" T="51" Pressure="128"/>
		<Point X="261" Y="521" T="52" Pressure="128"/>
		<Point X="260" Y="522" T="53" Pressure="128"/>
		<Point X="260" Y="523" T="54" Pressure="128"/>
		<Point X="259" Y="523" T="55" Pressure="128"/>
		<Point X="258" Y="524" T="56" Pressure="128"/>
		<Point X="257" Y="525" T="57" Pressure="128"/>
		<Point X="256" Y="525" T="58" Pressure="128"/>
		<Point X="256" Y="526" T="59" Pressure="128"/>
		<Point X="257" Y="526" T="60" Pressure="128"/>
		<Point X="259" Y="526" T="61" Pressure="128"/>
		<Point X="260" Y="525" T="62" Pressure="128"/>
		<Point X="262" Y="525" T="63" Pressure="128"/>
		<Point X="263" Y="523" T="64" Pressure="128"/>
		<Point X="264" Y="523" T="65" Pressure="128"/>
		<Point X="266" Y="522" T="66" Pressure="128"/>
		<Point X="267" Y="521" T="67" Pressure="128"/>
		<Point X="269" Y="520" T="68" Pressure="128"/>
		<Point X="271" Y="519" T="69" Pressure="128"/>
		<Point X="273" Y="517" T="70" Pressure="128"/>
		<Point X="275" Y="516" T="71" Pressure="128"/>
		<Point X="277" Y="515" T="72" Pressure="128"/>
		<Point X="279" Y="513" T="73" Pressure="128"/>
		<Point X="282" Y="512" T="74" Pressure="128"/>
		<Point X="285" Y="511" T="75" Pressure="128"/>
		<Point X="289" Y="509" T="76" Pressure="128"/>
		<Point X="292" Y="508" T="77" Pressure="128"/>
		<Point X="293" Y="508" T="78" Pressure="128"/>
		<Point X="296" Y="508" T="79" Pressure="128"/>
		<Point X="298" Y="507" T="80" Pressure="128"/>
		<Point X="301" Y="507" T="81" Pressure="128"/>
		<Point X="302" Y="507" T="82" Pressure="128"/>
		<Point X="304" Y="508" T="83" Pressure="128"/>
		<Point X="306" Y="508" T="84" Pressure="128"/>
		<Point X="308" Y="510" T="85" Pressure="128"/>
		<Point X="309" Y="511" T="86" Pressure="128"/>
		<Point X="311" Y="512" T="87" Pressure="128"/>
		<Point X="312" Y="514" T="88" Pressure="128"/>
		<Point X="313" Y="515" T="89" Pressure="128"/>
		<Point X="315" Y="517" T="90" Pressure="128"/>
		<Point X="316" Y="519" T="91" Pressure="128"/>
		<Point X="316" Y="521" T="92" Pressure="128"/>
		<Point X="317" Y="523" T="93" Pressure="128"/>
		<Point X="317" Y="525" T="94" Pressure="128"/>
		<Point X="318" Y="529" T="95" Pressure="128"/>
		<Point X="318" Y="531" T="96" Pressure="128"/>
		<Point X="318" Y="533" T="97" Pressure="128"/>
		<Point X="318" Y="535" T="98" Pressure="128"/>
		<Point X="318" Y="537" T="99" Pressure="128"/>
		<Point X="317" Y="538" T="100" Pressure="128"/>
		<Point X="316" Y="540" T="101" Pressure="128"/>
		<Point X="315" Y="542" T="102" Pressure="128"/>
		<Point X="314" Y="544" T="103" Pressure="128"/>
		<Point X="312" Y="546" T="104" Pressure="128"/>
		<Point X="311" Y="547" T="105" Pressure="128"/>
		<Point X="309" Y="548" T="106" Pressure="128"/>
		<Point X="307" Y="550" T="107" Pressure="128"/>
		<Point X="305" Y="551" T="108" Pressure="128"/>
		<Point X="302" Y="552" T="109" Pressure="128"/>
		<Point X="300" Y="553" T="110" Pressure="128"/>
		<Point X="297" Y="553" T="111" Pressure="128"/>
		<Point X="295" Y="555" T="112" Pressure="128"/>
		<Point X="292" Y="555" T="113" Pressure="128"/>
		<Point X="289" Y="556" T="114" Pressure="128"/>
		<Point X="285" Y="557" T="115" Pressure="128"/>
		<Point X="282" Y="557" T="116" Pressure="128"/>
		<Point X="279" Y="557" T="117" Pressure="128"/>
		<Point X="276" Y="558" T="118" Pressure="128"/>
		<Point X="273" Y="558" T="119" Pressure="128"/>
		<Point X="270" Y="558" T="120" Pressure="128"/>
		<Point X="267" Y="558" T="121" Pressure="128"/>
		<Point X="263" Y="558" T="122" Pressure="128"/>
		<Point X="262" Y="558" T="123" Pressure="128"/>
		<Point X="261" Y="559" T="124" Pressure="128"/>
		<Point X="260" Y="560" T="125" Pressure="128"/>
		<Point X="260" Y="561" T="126" Pressure="128"/>
		<Point X="261" Y="561" T="127" Pressure="128"/>
		<Point X="262" Y="562" T="128" Pressure="128"/>
		<Point X="263" Y="562" T="129" Pressure="128"/>
	</Stroke>
</Gesture>
